bi/__init__.py
bi/__main__.py
bi/bi.py
bi_lang-0.1.4.dist-info/licenses/LICENSE
bi_lang-0.1.4.dist-info/METADATA
bi_lang-0.1.4.dist-info/WHEEL
bi_lang-0.1.4.dist-info/entry_points.txt
bi_lang-0.1.4.dist-info/top_level.txt
bi_lang-0.1.4.dist-info/RECORD
