Metadata-Version: 2.4
Name: bi-lang
Version: 0.1.4
Summary: Python interpreter for Tsoding's B language
Home-page: https://github.com/roypery2010/bi-lang
Author: Roy Perry
License: MIT
Classifier: Programming Language :: Python :: 3
Classifier: License :: OSI Approved :: MIT License
Classifier: Operating System :: OS Independent
Requires-Python: >=3.7
License-File: LICENSE
Dynamic: author
Dynamic: classifier
Dynamic: description
Dynamic: description-content-type
Dynamic: home-page
Dynamic: license
Dynamic: license-file
Dynamic: requires-python
Dynamic: summary
